AMAS/__init__.py
AMAS/annotation_maker.py
AMAS/constants.py
AMAS/iterator.py
AMAS/reaction_annotation.py
AMAS/recommend_annotation
AMAS/recommend_annotation.bat
AMAS/recommend_annotation.py
AMAS/recommend_reaction
AMAS/recommend_reaction.py
AMAS/recommend_reactions
AMAS/recommend_reactions.bat
AMAS/recommend_reactions.py
AMAS/recommend_species
AMAS/recommend_species.bat
AMAS/recommend_species.py
AMAS/recommender.py
AMAS/species_annotation.py
AMAS/tools.py
AMAS/update_annotation
AMAS/update_annotation.bat
AMAS/update_annotation.py
AMAS/files/charcount_df_scaled.lzma
AMAS/files/chebi2label.lzma
AMAS/files/chebi_low_synonyms_comp.lzma
AMAS/files/chebi_shortened_formula_comp.lzma
AMAS/files/data2ref_mat.lzma
AMAS/files/ec2mrhea.lzma
AMAS/files/kegg2mrhea.lzma
AMAS/files/mrhea2chebi_prime.lzma
AMAS/files/mrhea2eckegg.lzma
AMAS/files/reactions_rf_fitted.lzma
AMAS/files/ref_nonzero_cols.lzma
AMAS/files/rhea2label.lzma
AMAS/files/rhea_all2master.lzma
AMAS/files/species_rf_fitted.lzma
AMAS_sb-1.0.1.data/scripts/recommend_annotation
AMAS_sb-1.0.1.data/scripts/recommend_annotation.bat
AMAS_sb-1.0.1.data/scripts/recommend_annotation.py
AMAS_sb-1.0.1.data/scripts/recommend_reaction
AMAS_sb-1.0.1.data/scripts/recommend_reaction.py
AMAS_sb-1.0.1.data/scripts/recommend_reactions
AMAS_sb-1.0.1.data/scripts/recommend_reactions.bat
AMAS_sb-1.0.1.data/scripts/recommend_reactions.py
AMAS_sb-1.0.1.data/scripts/recommend_species
AMAS_sb-1.0.1.data/scripts/recommend_species.bat
AMAS_sb-1.0.1.data/scripts/recommend_species.py
AMAS_sb-1.0.1.data/scripts/update_annotation
AMAS_sb-1.0.1.data/scripts/update_annotation.bat
AMAS_sb-1.0.1.data/scripts/update_annotation.py
AMAS_sb-1.0.1.dist-info/LICENSE
AMAS_sb-1.0.1.dist-info/METADATA
AMAS_sb-1.0.1.dist-info/WHEEL
AMAS_sb-1.0.1.dist-info/top_level.txt
AMAS_sb-1.0.1.dist-info/RECORD
