Metadata-Version: 2.1
Name: AMAS-sb
Version: 1.0.1
Summary: AMAS (Automatic Model Annotation System)
Home-page: https://github.com/sys-bio/AMAS
Author: Woosub Shin
Author-email: woosubs@umich.edu
Classifier: Development Status :: 3 - Alpha
Classifier: Intended Audience :: Developers
Classifier: Topic :: Scientific/Engineering :: Bio-Informatics
Classifier: License :: OSI Approved :: MIT License
Classifier: Programming Language :: Python :: 3.8
Classifier: Programming Language :: Python :: 3.9
License-File: LICENSE
Requires-Dist: compress-pickle
Requires-Dist: editdistance
Requires-Dist: nose
Requires-Dist: numpy
Requires-Dist: pandas
Requires-Dist: python-libsbml
Requires-Dist: pyyaml
